artagger
