Metadata-Version: 1.1
Name: artagger
Version: 0.1.0.3
Summary: RDRPOSTagger Implementation.
Home-page: https://github.com/franziz/artagger/
Author: Frans Huang
Author-email: franssiswanto@gmail.com
License: MIT
Platform: UNKNOWN
Classifier: Programming Language :: Python :: 3
Classifier: Intended Audience :: Developers
